<?xml version="1.0" encoding="UTF-8" standalone="no"?><template name="smen"><region name="Region 1"><position x1="258" x2="842" y1="353" y2="415"/></region><region name="Region 2"><position x1="270" x2="580" y1="422" y2="476"/></region><region name="Region 3"><position x1="256" x2="494" y1="487" y2="539"/></region><region name="Region 4"><position x1="244" x2="415" y1="545" y2="603"/></region><region name="Region 5"><position x1="262" x2="837" y1="742" y2="791"/></region><region name="Region 6"><position x1="1085" x2="1258" y1="619" y2="661"/></region><region name="Region 7"><position x1="1261" x2="1361" y1="492" y2="532"/></region><region name="Region 8"><position x1="799" x2="1027" y1="1312" y2="1349"/></region><region name="Region 9"><position x1="612" x2="868" y1="1376" y2="1413"/></region></template>